normalize/__init__.py
normalize/letters.yml
text_normalize-1.0.1.dist-info/LICENSE
text_normalize-1.0.1.dist-info/METADATA
text_normalize-1.0.1.dist-info/WHEEL
text_normalize-1.0.1.dist-info/top_level.txt
text_normalize-1.0.1.dist-info/RECORD
