Metadata-Version: 2.1
Name: text-normalize
Version: 1.0.1
Summary: Normalize text to remove unicode lookalike characters.
Home-page: https://github.com/vcokltfre/normalize
Author: vcokltfre
Author-email: UNKNOWN
License: MIT
Platform: UNKNOWN
Requires-Dist: pyyaml
